prediction/__init__.py
prediction/admin.py
prediction/apps.py
prediction/asgi.py
prediction/forms.py
prediction/models.py
prediction/serializers.py
prediction/settings.py
prediction/tests.py
prediction/urls.py
prediction/views.py
prediction/wsgi.py
prediction/migrations/0001_initial.py
prediction/migrations/__init__.py
avocado_price_predictor-0.0.2.dist-info/LICENSE
avocado_price_predictor-0.0.2.dist-info/METADATA
avocado_price_predictor-0.0.2.dist-info/WHEEL
avocado_price_predictor-0.0.2.dist-info/top_level.txt
avocado_price_predictor-0.0.2.dist-info/RECORD
